{"SubcategoryID":278,"SubcategoryName":"WalkyTalky","PropertyName":"TwoWayRadioandAccessoryChannels","IsAdvancedSearch":0,"IsGroupBy":0,"IsRequired":0,"PropertyValueList":["10 Billion Channels","10 Channels","11 Channels","12 Channels","14 Channels","15 Channels","16 Channels","18 Channels","20 Channels","200 Channels","22 Channels","24 Channels","25 Channels","25000 Channels","26 Channels","28 Channels","30 Channels","300 Channels","36 Channels","40 Channels","42 Channels","50 Channels","8 Channels","88 Channels"]}