[{"SubcategoryID":3419,"SubcategoryName":"DockEquipmentDrums","PropertyName":"ManufacturerWarrantyParts","IsAdvancedSearch":0,"IsGroupBy":0,"IsRequired":0},{"SubcategoryID":3419,"SubcategoryName":"DockEquipmentDrums","PropertyName":"ManufacturerWarrantyLabor","IsAdvancedSearch":0,"IsGroupBy":0,"IsRequired":0},{"SubcategoryID":3419,"SubcategoryName":"DockEquipmentDrums","PropertyName":"GlobalWatts","IsAdvancedSearch":0,"IsGroupBy":0,"IsRequired":0},{"SubcategoryID":3419,"SubcategoryName":"DockEquipmentDrums","PropertyName":"GlobalFeatures","IsAdvancedSearch":0,"IsGroupBy":0,"IsRequired":0},{"SubcategoryID":3419,"SubcategoryName":"DockEquipmentDrums","PropertyName":"GlobalAmps","IsAdvancedSearch":0,"IsGroupBy":0,"IsRequired":0},{"SubcategoryID":3419,"SubcategoryName":"DockEquipmentDrums","PropertyName":"GlobalVoltage","IsAdvancedSearch":0,"IsGroupBy":0,"IsRequired":0},{"SubcategoryID":3419,"SubcategoryName":"DockEquipmentDrums","PropertyName":"GlobalMaterial","IsAdvancedSearch":0,"IsGroupBy":0,"IsRequired":0},{"SubcategoryID":3419,"SubcategoryName":"DockEquipmentDrums","PropertyName":"GlobalFinish","IsAdvancedSearch":0,"IsGroupBy":0,"IsRequired":0},{"SubcategoryID":3419,"SubcategoryName":"DockEquipmentDrums","PropertyName":"GlobalBrand","IsAdvancedSearch":0,"IsGroupBy":0,"IsRequired":0},{"SubcategoryID":3419,"SubcategoryName":"DockEquipmentDrums","PropertyName":"GlobalModel","IsAdvancedSearch":0,"IsGroupBy":0,"IsRequired":0},{"SubcategoryID":3419,"SubcategoryName":"DockEquipmentDrums","PropertyName":"DockEquipmentType","IsAdvancedSearch":1,"IsGroupBy":0,"IsRequired":0},{"SubcategoryID":3419,"SubcategoryName":"DockEquipmentDrums","PropertyName":"DockEquipmentWattDensity","IsAdvancedSearch":0,"IsGroupBy":0,"IsRequired":0},{"SubcategoryID":3419,"SubcategoryName":"DockEquipmentDrums","PropertyName":"DockEquipmentCapacity","IsAdvancedSearch":0,"IsGroupBy":0,"IsRequired":0},{"SubcategoryID":3419,"SubcategoryName":"DockEquipmentDrums","PropertyName":"DockEquipmentSizeDimensions","IsAdvancedSearch":0,"IsGroupBy":0,"IsRequired":0},{"SubcategoryID":3419,"SubcategoryName":"DockEquipmentDrums","PropertyName":"GlobalElectricalOutletPlugType","IsAdvancedSearch":0,"IsGroupBy":0,"IsRequired":0}]