[{"SubcategoryID":3440,"SubcategoryName":"IndustrialPlumbingToolsEquipment","PropertyName":"ManufacturerWarrantyParts","IsAdvancedSearch":0,"IsGroupBy":0,"IsRequired":0},{"SubcategoryID":3440,"SubcategoryName":"IndustrialPlumbingToolsEquipment","PropertyName":"ManufacturerWarrantyLabor","IsAdvancedSearch":0,"IsGroupBy":0,"IsRequired":0},{"SubcategoryID":3440,"SubcategoryName":"IndustrialPlumbingToolsEquipment","PropertyName":"GlobalSellingUnit","IsAdvancedSearch":0,"IsGroupBy":0,"IsRequired":0},{"SubcategoryID":3440,"SubcategoryName":"IndustrialPlumbingToolsEquipment","PropertyName":"GlobalCompatibilityFitment","IsAdvancedSearch":0,"IsGroupBy":0,"IsRequired":0},{"SubcategoryID":3440,"SubcategoryName":"IndustrialPlumbingToolsEquipment","PropertyName":"GlobalWeight","IsAdvancedSearch":0,"IsGroupBy":0,"IsRequired":0},{"SubcategoryID":3440,"SubcategoryName":"IndustrialPlumbingToolsEquipment","PropertyName":"GlobalAmps","IsAdvancedSearch":0,"IsGroupBy":0,"IsRequired":0},{"SubcategoryID":3440,"SubcategoryName":"IndustrialPlumbingToolsEquipment","PropertyName":"GlobalVoltage","IsAdvancedSearch":0,"IsGroupBy":0,"IsRequired":0},{"SubcategoryID":3440,"SubcategoryName":"IndustrialPlumbingToolsEquipment","PropertyName":"GlobalHorsepower","IsAdvancedSearch":0,"IsGroupBy":0,"IsRequired":0},{"SubcategoryID":3440,"SubcategoryName":"IndustrialPlumbingToolsEquipment","PropertyName":"GlobalItemCount","IsAdvancedSearch":0,"IsGroupBy":0,"IsRequired":0},{"SubcategoryID":3440,"SubcategoryName":"IndustrialPlumbingToolsEquipment","PropertyName":"GlobalMaterial","IsAdvancedSearch":0,"IsGroupBy":0,"IsRequired":0},{"SubcategoryID":3440,"SubcategoryName":"IndustrialPlumbingToolsEquipment","PropertyName":"GlobalBrand","IsAdvancedSearch":0,"IsGroupBy":0,"IsRequired":0},{"SubcategoryID":3440,"SubcategoryName":"IndustrialPlumbingToolsEquipment","PropertyName":"GlobalModel","IsAdvancedSearch":0,"IsGroupBy":0,"IsRequired":0},{"SubcategoryID":3440,"SubcategoryName":"IndustrialPlumbingToolsEquipment","PropertyName":"PlumbingToolType","IsAdvancedSearch":1,"IsGroupBy":0,"IsRequired":0},{"SubcategoryID":3440,"SubcategoryName":"IndustrialPlumbingToolsEquipment","PropertyName":"PlumbingToolSeries","IsAdvancedSearch":0,"IsGroupBy":0,"IsRequired":0},{"SubcategoryID":3440,"SubcategoryName":"IndustrialPlumbingToolsEquipment","PropertyName":"PlumbingToolSizeDimensions","IsAdvancedSearch":0,"IsGroupBy":0,"IsRequired":0},{"SubcategoryID":3440,"SubcategoryName":"IndustrialPlumbingToolsEquipment","PropertyName":"PlumbingToolStyle","IsAdvancedSearch":1,"IsGroupBy":0,"IsRequired":0},{"SubcategoryID":3440,"SubcategoryName":"IndustrialPlumbingToolsEquipment","PropertyName":"PlumbingToolLineCableCapacity","IsAdvancedSearch":1,"IsGroupBy":0,"IsRequired":0},{"SubcategoryID":3440,"SubcategoryName":"IndustrialPlumbingToolsEquipment","PropertyName":"PlumbingToolCableLength","IsAdvancedSearch":0,"IsGroupBy":0,"IsRequired":0},{"SubcategoryID":3440,"SubcategoryName":"IndustrialPlumbingToolsEquipment","PropertyName":"PlumbingToolRotationsperMinute","IsAdvancedSearch":0,"IsGroupBy":0,"IsRequired":0},{"SubcategoryID":3440,"SubcategoryName":"IndustrialPlumbingToolsEquipment","PropertyName":"PlumbingToolCablesIncluded","IsAdvancedSearch":0,"IsGroupBy":0,"IsRequired":0},{"SubcategoryID":3440,"SubcategoryName":"IndustrialPlumbingToolsEquipment","PropertyName":"PlumbingToolPressure","IsAdvancedSearch":1,"IsGroupBy":0,"IsRequired":0},{"SubcategoryID":3440,"SubcategoryName":"IndustrialPlumbingToolsEquipment","PropertyName":"PlumbingToolHoseSize","IsAdvancedSearch":0,"IsGroupBy":0,"IsRequired":0},{"SubcategoryID":3440,"SubcategoryName":"IndustrialPlumbingToolsEquipment","PropertyName":"PlumbingToolApplication","IsAdvancedSearch":1,"IsGroupBy":0,"IsRequired":0},{"SubcategoryID":3440,"SubcategoryName":"IndustrialPlumbingToolsEquipment","PropertyName":"PlumbingToolBendRadius","IsAdvancedSearch":0,"IsGroupBy":0,"IsRequired":0},{"SubcategoryID":3440,"SubcategoryName":"IndustrialPlumbingToolsEquipment","PropertyName":"PlumbingToolWireGauge","IsAdvancedSearch":0,"IsGroupBy":0,"IsRequired":0},{"SubcategoryID":3440,"SubcategoryName":"IndustrialPlumbingToolsEquipment","PropertyName":"PlumbingToolOperatingTemperature","IsAdvancedSearch":0,"IsGroupBy":0,"IsRequired":0},{"SubcategoryID":3440,"SubcategoryName":"IndustrialPlumbingToolsEquipment","PropertyName":"PlumbingToolVideoResolution","IsAdvancedSearch":0,"IsGroupBy":0,"IsRequired":0},{"SubcategoryID":3440,"SubcategoryName":"IndustrialPlumbingToolsEquipment","PropertyName":"PlumbingToolPipeTubeCapacity","IsAdvancedSearch":0,"IsGroupBy":0,"IsRequired":0},{"SubcategoryID":3440,"SubcategoryName":"IndustrialPlumbingToolsEquipment","PropertyName":"PlumbingToolBladeMaterial","IsAdvancedSearch":0,"IsGroupBy":0,"IsRequired":0},{"SubcategoryID":3440,"SubcategoryName":"IndustrialPlumbingToolsEquipment","PropertyName":"PlumbingToolCuttingCapacityOD","IsAdvancedSearch":0,"IsGroupBy":0,"IsRequired":0},{"SubcategoryID":3440,"SubcategoryName":"IndustrialPlumbingToolsEquipment","PropertyName":"PlumbingToolSwingRadiusatMaxCapacity","IsAdvancedSearch":1,"IsGroupBy":0,"IsRequired":0},{"SubcategoryID":3440,"SubcategoryName":"IndustrialPlumbingToolsEquipment","PropertyName":"GlobalElectricalOutletPlugType","IsAdvancedSearch":0,"IsGroupBy":0,"IsRequired":0}]