[{"SubcategoryID":1928,"SubcategoryName":"HIAntennasWiresFittings","PropertyName":"HIAntennasWiresFittingsBrand","IsAdvancedSearch":0,"IsGroupBy":0,"IsRequired":0},{"SubcategoryID":1928,"SubcategoryName":"HIAntennasWiresFittings","PropertyName":"HIAntennasWiresFittingsModel","IsAdvancedSearch":0,"IsGroupBy":0,"IsRequired":0},{"SubcategoryID":1928,"SubcategoryName":"HIAntennasWiresFittings","PropertyName":"HIAntennasWiresFittingsSizeDimensions","IsAdvancedSearch":0,"IsGroupBy":0,"IsRequired":0},{"SubcategoryID":1928,"SubcategoryName":"HIAntennasWiresFittings","PropertyName":"HIAntennasWiresFittingsAntennaReception","IsAdvancedSearch":1,"IsGroupBy":0,"IsRequired":0},{"SubcategoryID":1928,"SubcategoryName":"HIAntennasWiresFittings","PropertyName":"HIAntennasWiresFittingsAdapterType","IsAdvancedSearch":1,"IsGroupBy":0,"IsRequired":0},{"SubcategoryID":1928,"SubcategoryName":"HIAntennasWiresFittings","PropertyName":"HIAntennasWiresFittingsMaximumVoltage","IsAdvancedSearch":0,"IsGroupBy":0,"IsRequired":0},{"SubcategoryID":1928,"SubcategoryName":"HIAntennasWiresFittings","PropertyName":"HIAntennasWiresFittingsMaximumWireCapacity","IsAdvancedSearch":0,"IsGroupBy":0,"IsRequired":0},{"SubcategoryID":1928,"SubcategoryName":"HIAntennasWiresFittings","PropertyName":"HIAntennasWiresFittingsMinimumWireCapacity","IsAdvancedSearch":0,"IsGroupBy":0,"IsRequired":0},{"SubcategoryID":1928,"SubcategoryName":"HIAntennasWiresFittings","PropertyName":"HIAntennasWiresFittingsColorFinish","IsAdvancedSearch":0,"IsGroupBy":0,"IsRequired":0},{"SubcategoryID":1928,"SubcategoryName":"HIAntennasWiresFittings","PropertyName":"HIAntennasWiresFittingsColorMapping","IsAdvancedSearch":0,"IsGroupBy":0,"IsRequired":0},{"SubcategoryID":1928,"SubcategoryName":"HIAntennasWiresFittings","PropertyName":"HIAntennasWiresFittingsULSafetyListing","IsAdvancedSearch":1,"IsGroupBy":0,"IsRequired":0},{"SubcategoryID":1928,"SubcategoryName":"HIAntennasWiresFittings","PropertyName":"HIAntennasWiresFittingsCSASafetyListing","IsAdvancedSearch":1,"IsGroupBy":0,"IsRequired":0},{"SubcategoryID":1928,"SubcategoryName":"HIAntennasWiresFittings","PropertyName":"HIAntennasWiresFittingsETLSafetyListing","IsAdvancedSearch":1,"IsGroupBy":0,"IsRequired":0},{"SubcategoryID":1928,"SubcategoryName":"HIAntennasWiresFittings","PropertyName":"HIAntennasWiresFittingsCESafetyListing","IsAdvancedSearch":1,"IsGroupBy":0,"IsRequired":0},{"SubcategoryID":1928,"SubcategoryName":"HIAntennasWiresFittings","PropertyName":"HIAntennasWiresFittingsItemCount","IsAdvancedSearch":0,"IsGroupBy":0,"IsRequired":0},{"SubcategoryID":1928,"SubcategoryName":"HIAntennasWiresFittings","PropertyName":"HIAntennasWiresFittingsMaterial","IsAdvancedSearch":0,"IsGroupBy":0,"IsRequired":0},{"SubcategoryID":1928,"SubcategoryName":"HIAntennasWiresFittings","PropertyName":"HIAntennasWiresFittingsEnergyStarQualified","IsAdvancedSearch":1,"IsGroupBy":0,"IsRequired":0},{"SubcategoryID":1928,"SubcategoryName":"HIAntennasWiresFittings","PropertyName":"HIAntennasWiresFittingsSellingUnit","IsAdvancedSearch":1,"IsGroupBy":0,"IsRequired":0},{"SubcategoryID":1928,"SubcategoryName":"HIAntennasWiresFittings","PropertyName":"HIAntennasWiresFittingsType","IsAdvancedSearch":1,"IsGroupBy":0,"IsRequired":0},{"SubcategoryID":1928,"SubcategoryName":"HIAntennasWiresFittings","PropertyName":"HIAntennasWiresFittingsFeatures","IsAdvancedSearch":0,"IsGroupBy":0,"IsRequired":0},{"SubcategoryID":1928,"SubcategoryName":"HIAntennasWiresFittings","PropertyName":"SportsGlobalSportsTeam","IsAdvancedSearch":0,"IsGroupBy":0,"IsRequired":0},{"SubcategoryID":1928,"SubcategoryName":"HIAntennasWiresFittings","PropertyName":"SportsGlobalSportsLeague","IsAdvancedSearch":0,"IsGroupBy":0,"IsRequired":0},{"SubcategoryID":1928,"SubcategoryName":"HIAntennasWiresFittings","PropertyName":"GlobalElectricalOutletPlugType","IsAdvancedSearch":0,"IsGroupBy":0,"IsRequired":0}]