[{"SubcategoryID":2089,"SubcategoryName":"HITubShowerParts","PropertyName":"HITubShowerPartsBrand","IsAdvancedSearch":0,"IsGroupBy":0,"IsRequired":0},{"SubcategoryID":2089,"SubcategoryName":"HITubShowerParts","PropertyName":"HITubShowerPartsFeatures","IsAdvancedSearch":0,"IsGroupBy":0,"IsRequired":0},{"SubcategoryID":2089,"SubcategoryName":"HITubShowerParts","PropertyName":"HITubShowerPartsModel","IsAdvancedSearch":0,"IsGroupBy":0,"IsRequired":0},{"SubcategoryID":2089,"SubcategoryName":"HITubShowerParts","PropertyName":"HITubShowerPartsSellingUnit","IsAdvancedSearch":1,"IsGroupBy":0,"IsRequired":0},{"SubcategoryID":2089,"SubcategoryName":"HITubShowerParts","PropertyName":"HITubShowerPartsType","IsAdvancedSearch":1,"IsGroupBy":0,"IsRequired":0},{"SubcategoryID":2089,"SubcategoryName":"HITubShowerParts","PropertyName":"HITubShowerPartsFinish","IsAdvancedSearch":0,"IsGroupBy":1,"IsRequired":0},{"SubcategoryID":2089,"SubcategoryName":"HITubShowerParts","PropertyName":"SportsGlobalSportsTeam","IsAdvancedSearch":0,"IsGroupBy":0,"IsRequired":0},{"SubcategoryID":2089,"SubcategoryName":"HITubShowerParts","PropertyName":"SportsGlobalSportsLeague","IsAdvancedSearch":0,"IsGroupBy":0,"IsRequired":0},{"SubcategoryID":2089,"SubcategoryName":"HITubShowerParts","PropertyName":"GlobalElectricalOutletPlugType","IsAdvancedSearch":0,"IsGroupBy":0,"IsRequired":0}]