[{"SubcategoryID":847,"SubcategoryName":"LightingStudio","PropertyName":"LSType","IsAdvancedSearch":1,"IsGroupBy":0,"IsRequired":0},{"SubcategoryID":847,"SubcategoryName":"LightingStudio","PropertyName":"ManufacturerWarrantyParts","IsAdvancedSearch":0,"IsGroupBy":0,"IsRequired":0},{"SubcategoryID":847,"SubcategoryName":"LightingStudio","PropertyName":"ManufacturerWarrantyLabor","IsAdvancedSearch":0,"IsGroupBy":0,"IsRequired":0},{"SubcategoryID":847,"SubcategoryName":"LightingStudio","PropertyName":"LSBrand","IsAdvancedSearch":0,"IsGroupBy":0,"IsRequired":0},{"SubcategoryID":847,"SubcategoryName":"LightingStudio","PropertyName":"LSModel","IsAdvancedSearch":0,"IsGroupBy":0,"IsRequired":0},{"SubcategoryID":847,"SubcategoryName":"LightingStudio","PropertyName":"LSContains","IsAdvancedSearch":0,"IsGroupBy":0,"IsRequired":0},{"SubcategoryID":847,"SubcategoryName":"LightingStudio","PropertyName":"LSBase","IsAdvancedSearch":0,"IsGroupBy":0,"IsRequired":0},{"SubcategoryID":847,"SubcategoryName":"LightingStudio","PropertyName":"LSConstruction","IsAdvancedSearch":0,"IsGroupBy":0,"IsRequired":0},{"SubcategoryID":847,"SubcategoryName":"LightingStudio","PropertyName":"LSDimension","IsAdvancedSearch":0,"IsGroupBy":0,"IsRequired":0},{"SubcategoryID":847,"SubcategoryName":"LightingStudio","PropertyName":"LSColor","IsAdvancedSearch":0,"IsGroupBy":0,"IsRequired":0},{"SubcategoryID":847,"SubcategoryName":"LightingStudio","PropertyName":"LSVoltage","IsAdvancedSearch":0,"IsGroupBy":0,"IsRequired":0},{"SubcategoryID":847,"SubcategoryName":"LightingStudio","PropertyName":"LSWattage","IsAdvancedSearch":0,"IsGroupBy":0,"IsRequired":0},{"SubcategoryID":847,"SubcategoryName":"LightingStudio","PropertyName":"LSCordLength","IsAdvancedSearch":0,"IsGroupBy":0,"IsRequired":0},{"SubcategoryID":847,"SubcategoryName":"LightingStudio","PropertyName":"LSSpecification","IsAdvancedSearch":0,"IsGroupBy":0,"IsRequired":0},{"SubcategoryID":847,"SubcategoryName":"LightingStudio","PropertyName":"LSFeatures","IsAdvancedSearch":0,"IsGroupBy":0,"IsRequired":0},{"SubcategoryID":847,"SubcategoryName":"LightingStudio","PropertyName":"LSPackageContent","IsAdvancedSearch":0,"IsGroupBy":0,"IsRequired":0},{"SubcategoryID":847,"SubcategoryName":"LightingStudio","PropertyName":"LSColorTemperature","IsAdvancedSearch":0,"IsGroupBy":0,"IsRequired":0},{"SubcategoryID":847,"SubcategoryName":"LightingStudio","PropertyName":"LSMTBF","IsAdvancedSearch":0,"IsGroupBy":0,"IsRequired":0},{"SubcategoryID":847,"SubcategoryName":"LightingStudio","PropertyName":"LSCompatibility","IsAdvancedSearch":0,"IsGroupBy":0,"IsRequired":0},{"SubcategoryID":847,"SubcategoryName":"LightingStudio","PropertyName":"SportsGlobalSportsTeam","IsAdvancedSearch":0,"IsGroupBy":0,"IsRequired":0},{"SubcategoryID":847,"SubcategoryName":"LightingStudio","PropertyName":"LSPart","IsAdvancedSearch":0,"IsGroupBy":0,"IsRequired":0},{"SubcategoryID":847,"SubcategoryName":"LightingStudio","PropertyName":"SportsGlobalSportsLeague","IsAdvancedSearch":0,"IsGroupBy":0,"IsRequired":0},{"SubcategoryID":847,"SubcategoryName":"LightingStudio","PropertyName":"GlobalElectricalOutletPlugType","IsAdvancedSearch":0,"IsGroupBy":0,"IsRequired":0}]