[{"SubcategoryID":743,"SubcategoryName":"CanistersVacuums","PropertyName":"ManufacturerWarrantyParts","IsAdvancedSearch":0,"IsGroupBy":0,"IsRequired":0},{"SubcategoryID":743,"SubcategoryName":"CanistersVacuums","PropertyName":"ManufacturerWarrantyLabor","IsAdvancedSearch":0,"IsGroupBy":0,"IsRequired":0},{"SubcategoryID":743,"SubcategoryName":"CanistersVacuums","PropertyName":"FloorCareBrand","IsAdvancedSearch":0,"IsGroupBy":0,"IsRequired":0},{"SubcategoryID":743,"SubcategoryName":"CanistersVacuums","PropertyName":"FloorCareName","IsAdvancedSearch":0,"IsGroupBy":0,"IsRequired":0},{"SubcategoryID":743,"SubcategoryName":"CanistersVacuums","PropertyName":"FloorCareModel","IsAdvancedSearch":0,"IsGroupBy":0,"IsRequired":0},{"SubcategoryID":743,"SubcategoryName":"CanistersVacuums","PropertyName":"FloorCareFeatures","IsAdvancedSearch":0,"IsGroupBy":0,"IsRequired":0},{"SubcategoryID":743,"SubcategoryName":"CanistersVacuums","PropertyName":"FloorCareColor","IsAdvancedSearch":0,"IsGroupBy":1,"IsRequired":0},{"SubcategoryID":743,"SubcategoryName":"CanistersVacuums","PropertyName":"FloorCareBagless","IsAdvancedSearch":1,"IsGroupBy":0,"IsRequired":0},{"SubcategoryID":743,"SubcategoryName":"CanistersVacuums","PropertyName":"FloorCareMotorAmperage","IsAdvancedSearch":0,"IsGroupBy":0,"IsRequired":0},{"SubcategoryID":743,"SubcategoryName":"CanistersVacuums","PropertyName":"FloorCareMotorVolts","IsAdvancedSearch":0,"IsGroupBy":0,"IsRequired":0},{"SubcategoryID":743,"SubcategoryName":"CanistersVacuums","PropertyName":"FloorCareMotorWattage","IsAdvancedSearch":0,"IsGroupBy":0,"IsRequired":0},{"SubcategoryID":743,"SubcategoryName":"CanistersVacuums","PropertyName":"FloorCareSuctionPower","IsAdvancedSearch":0,"IsGroupBy":0,"IsRequired":0},{"SubcategoryID":743,"SubcategoryName":"CanistersVacuums","PropertyName":"FloorCarePowerCordLength","IsAdvancedSearch":0,"IsGroupBy":0,"IsRequired":0},{"SubcategoryID":743,"SubcategoryName":"CanistersVacuums","PropertyName":"FloorCareCordless","IsAdvancedSearch":0,"IsGroupBy":0,"IsRequired":0},{"SubcategoryID":743,"SubcategoryName":"CanistersVacuums","PropertyName":"FloorCareNozzleWidth","IsAdvancedSearch":0,"IsGroupBy":0,"IsRequired":0},{"SubcategoryID":743,"SubcategoryName":"CanistersVacuums","PropertyName":"FloorCareEdgeCleaning","IsAdvancedSearch":0,"IsGroupBy":0,"IsRequired":0},{"SubcategoryID":743,"SubcategoryName":"CanistersVacuums","PropertyName":"FloorCareHeightAdjustment","IsAdvancedSearch":0,"IsGroupBy":0,"IsRequired":0},{"SubcategoryID":743,"SubcategoryName":"CanistersVacuums","PropertyName":"FloorCareHEPAFiltration","IsAdvancedSearch":1,"IsGroupBy":0,"IsRequired":0},{"SubcategoryID":743,"SubcategoryName":"CanistersVacuums","PropertyName":"FloorCareFullBagIndicator","IsAdvancedSearch":0,"IsGroupBy":0,"IsRequired":0},{"SubcategoryID":743,"SubcategoryName":"CanistersVacuums","PropertyName":"FloorCareHandle","IsAdvancedSearch":0,"IsGroupBy":0,"IsRequired":0},{"SubcategoryID":743,"SubcategoryName":"CanistersVacuums","PropertyName":"FloorCareHoseType","IsAdvancedSearch":0,"IsGroupBy":0,"IsRequired":0},{"SubcategoryID":743,"SubcategoryName":"CanistersVacuums","PropertyName":"FloorCareHoseLength","IsAdvancedSearch":0,"IsGroupBy":0,"IsRequired":0},{"SubcategoryID":743,"SubcategoryName":"CanistersVacuums","PropertyName":"FloorCareOnBoardToolsIncluded","IsAdvancedSearch":0,"IsGroupBy":0,"IsRequired":0},{"SubcategoryID":743,"SubcategoryName":"CanistersVacuums","PropertyName":"FloorCareAdditionalInformation","IsAdvancedSearch":0,"IsGroupBy":0,"IsRequired":0},{"SubcategoryID":743,"SubcategoryName":"CanistersVacuums","PropertyName":"FloorCareDimensions","IsAdvancedSearch":0,"IsGroupBy":0,"IsRequired":0},{"SubcategoryID":743,"SubcategoryName":"CanistersVacuums","PropertyName":"FloorCareWeight","IsAdvancedSearch":0,"IsGroupBy":0,"IsRequired":0},{"SubcategoryID":743,"SubcategoryName":"CanistersVacuums","PropertyName":"SportsGlobalSportsTeam","IsAdvancedSearch":0,"IsGroupBy":0,"IsRequired":0},{"SubcategoryID":743,"SubcategoryName":"CanistersVacuums","PropertyName":"SportsGlobalSportsLeague","IsAdvancedSearch":0,"IsGroupBy":0,"IsRequired":0},{"SubcategoryID":743,"SubcategoryName":"CanistersVacuums","PropertyName":"GlobalCommercialResidential","IsAdvancedSearch":1,"IsGroupBy":0,"IsRequired":0},{"SubcategoryID":743,"SubcategoryName":"CanistersVacuums","PropertyName":"GlobalElectricalOutletPlugType","IsAdvancedSearch":0,"IsGroupBy":0,"IsRequired":0}]