{"SubcategoryID":23,"SubcategoryName":"MP3MP4Players","PropertyName":"CNETMP3AudioFormats","IsAdvancedSearch":0,"IsGroupBy":0,"IsRequired":0,"PropertyValueList":["MP3","MP3\/AAC","MP3\/WAV","MP3\/WAV\/AAC\/Audible","MP3\/WAV\/AAC\/Audible\/AIFF","MP3\/WAV\/AAC\/Audible\/Apple Lossless\/AIFF","MP3\/WAV\/OGG","MP3\/WAV\/WMA with DRM\/OGG","MP3\/WAV\/WMA\/OGG\/APE\/FLAC\/ASF","MP3\/WAV\/WMA\/WMA with DRM\/Audible","MP3\/WAV\/WMA\/WMA with DRM\/OGG","MP3\/WMA","MP3\/WMA\/AAC","MP3\/WMA\/AAC-LC\/Linear PCM","MP3\/WMA\/AAC\/Audible","MP3\/WMA\/AAC\/Linear PCM","MP3\/WMA\/ADPCM","MP3\/WMA\/ASF","MP3\/WMA\/Audible","MP3\/WMA\/FLAC\/AAC\/APE","MP3\/WMA\/FLAC\/AAC\/APE\/OGG","MP3\/WMA\/OGG","MP3\/WMA\/OGG\/ASF","MP3\/WMA\/OGG\/FLAC\/Audible","MP3\/WMA\/Secure WMA\/Ogg Vorbis\/FLAC\/WAV\/Audible\/Po","MP3\/WMA\/WAV","MP3\/WMA\/WAV\/AAC","MP3\/WMA\/WAV\/AAC\/FLAC","MP3\/WMA\/WAV\/AAC\/OGG","MP3\/WMA\/WAV\/ACT","MP3\/WMA\/WAV\/ADPCM","MP3\/WMA\/WAV\/ADPCM\/Janus","MP3\/WMA\/WAV\/ADPCM\/WMA with DRM","MP3\/WMA\/WAV\/ADPCM\/WMA with DRM\/Audible","MP3\/WMA\/WAV\/ASF","MP3\/WMA\/WAV\/Audible","MP3\/WMA\/WAV\/FLAC\/APE","MP3\/WMA\/WAV\/OGG","MP3\/WMA\/WAV\/OGG\/ACT","MP3\/WMA\/WAV\/OGG\/APE","MP3\/WMA\/WAV\/OGG\/APE\/FLAC\/ASF\/MPC","MP3\/WMA\/WAV\/OGG\/FLAC","MP3\/WMA\/WAV\/OGG\/FLAC\/AAC","MP3\/WMA\/WAV\/OGG\/FLAC\/AAC\/RA","MP3\/WMA\/WAV\/OGG\/FLAC\/APE","MP3\/WMA\/WAV\/OGG\/FLAC\/APE\/AAC","MP3\/WMA\/WAV\/TVF","MP3\/WMA\/WAV\/WMA with DRM","MP3\/WMA\/WMA Lossless\/AAC-LC","MP3\/WMA\/WMA with DRM","MP3\/WMA\/WMA with DRM\/Audible","MP3\/WMA\/WMA with DRM\/OGG","WMA"]}