{"SubcategoryID":73,"SubcategoryName":"AddOnCards","PropertyName":"AddCardBrand","IsAdvancedSearch":0,"IsGroupBy":0,"IsRequired":0,"PropertyValueList":["acomdata","Adaptec","Addonics","ADS Tech","AFT","Airnet","Aluratek","AMS","Anker","Apollo","Apricorn","ASRock","Asus","Aten","Athenatech","AVS Gear","AZiO","B&B","BELKIN","Biostar","Brainboxes","Buffalo","BUSlink","BYTECC","C2G","CABLES UNLIMITED","Cavalry","Chenbro","CHP","Comtrol","CP TECHNOLOGIES","D-Link","Dialogic Corporation","Diamond","Digi International","ENCORE","Fieon Digital","Generic","GIGABYTE","Good Way Technology","GWC","HAWKING","HEISEI","HighPoint Technologies","HornetTek","HP","IBM","In Win","Inland","Intel","IOGEAR","Iomega","iStarUSA","JAHT","kanex","Kanguru","KEYSPAN","KINGWIN","Koutech","LaCie","LAVA Computer","Lenovo","Lexmark","Link Depot","LINKSKEY","Logisys","LSI LOGIC","macally","Macro Image","Magma","Manhattan","MASSCOOL","Mediasonic","MICRO INNOVATIONS","MicroNet","MSI","MTG","Mukii","NEC","One Stop Systems","ORICO","Patriot","Penguin Gear","Perle","PLANET","PNY","PPA","Pyro AV","Rosewill","SABRENT","SanMax","Sans Digital","SHARKOON","shintaro","SIIG","Silverstone","SNT","SoNNeT","StarTech","Sunbeam","SUNIX","Sunnytek","Sunrich\/ST Lab","SUPERMICRO","SYBA","Tek Republic","Transcend","TRENDnet","TRIPP LITE","Tyan","Ultra","Unincom","USRobotics","VANTEC","VIBE","VisionTek","Western Digital","Wintec","Zonet","Zurotech"]}