{"SubcategoryID":3319,"SubcategoryName":"FabricCraftsSewingAccessories","PropertyName":"FabricSizeDimensions","IsAdvancedSearch":1,"IsGroupBy":1,"IsRequired":0,"PropertyValueList":["1 1\/4 Oz.","1 in.","1 Yard","1\" Wide","1-1\/2\" Wide","1\/2 Oz.","10 Yards","100 Yards","11 Yards","12 in. X 12 in.","12 Yards","13 Yards","14 Yards","15 Yards","16 Yards","164 yards","17 Yards","18 Yards","19 Yards","2 1\/4 In.","2 1\/4 oz.","2 In.","2 In. X 1 1\/2 In.","2 mm","2 Yards","2\" Wide","2\/3 Oz.","20 Yards","2000 yards","21 Yards","22 Yards","23 Yards","24 Yards","25 Yards","26 Yards","27 Yards","28 Yards","29 Yards","3 In.","3 Mm","3 Yards","3\" Wide","3\/4\" Wide","30 Yards","31 Yards","32 Oz.","32 Yards","33 Yards","34 Yards","35 Yards","36 Yards","37 Yards","38 Yards","39 Yards","4 In.","4 Oz.","4 Yards","40 Yards","41 Yards","42 Yards","43 Yards","44 Yards","45 ml","45 Yards","5 In.","5 Mm","5 Yards","50 Yards","547 yards","6 Yards","60 Yards","7 In.","7 Yards","70 Yards","8 In.","8 In. X 45 In.","8 Oz.","8 oz. bottle","8 Yards","8.5 In. X 11 In.","80 Yards","9 In. X 12 In.","9 Yards","90 Yards","Variety"]}