{"SubcategoryID":1770,"SubcategoryName":"PlayCentersWalkers","PropertyName":"PlayCentersColor","IsAdvancedSearch":1,"IsGroupBy":1,"IsRequired":0,"PropertyValueList":["Ally","Aqua","Barcelona Bluegrass","Beige\/Orange","Bisque","Black","Black & Red","Black Gingham","Black Seat","Black\/Brown - Mesh","Black\/Red","Black\/Silver","Black\/White\/Red","Blue","Blue Clouds","Blue Plush","Blue\/Brown","Blue\/Gold","Bright","Brown","Brown\/Beige","Brown\/Tan","Butternut","Carnegie","Chestnut","Chili","City Blue","Clairmont","Clara","Coco Sorbet","Coconut White","Cog Wheels","Dark Blue\/Blue","Digital","Forecaster","Graham","Gray Gingham","Green","Green Jacks","Green Plush","Green\/Brown","Greige","Grey","Harvest Orange","Henna Brown","Inman Park","Jade","Jungle Crew","Khaki\/Beige","Lime","Luminosity","Mia","Milan","Mint","Mocha","Monkey","Multi","Multi-Color Plush","Multicolor","Navy","Oasis","Orange","Pastel","Pink","Pink Bear","Pink Seat","Pink Tea","Pink\/Brown","Pinstripe","Pistachio","Planet Blue Sky","Quick Silver","Red","Sachi","Sage","Sea Dreams","Silver","Silver Fireworks","Silver Plush","Sorbet","Splash","Tan","Townsend","Tropical Isle","Twilight","Wasabi","White","Wild Thing","Yellow"]}