[{"SubcategoryID":361,"SubcategoryName":"AnsweringMachines","PropertyName":"ManufacturerWarrantyParts","IsAdvancedSearch":0,"IsGroupBy":0,"IsRequired":0},{"SubcategoryID":361,"SubcategoryName":"AnsweringMachines","PropertyName":"ManufacturerWarrantyLabor","IsAdvancedSearch":0,"IsGroupBy":0,"IsRequired":0},{"SubcategoryID":361,"SubcategoryName":"AnsweringMachines","PropertyName":"AnsweringMachinesBrand","IsAdvancedSearch":0,"IsGroupBy":0,"IsRequired":0},{"SubcategoryID":361,"SubcategoryName":"AnsweringMachines","PropertyName":"AnsweringMachinesModel","IsAdvancedSearch":0,"IsGroupBy":0,"IsRequired":0},{"SubcategoryID":361,"SubcategoryName":"AnsweringMachines","PropertyName":"AnsweringMachinesBodyColor","IsAdvancedSearch":0,"IsGroupBy":0,"IsRequired":0},{"SubcategoryID":361,"SubcategoryName":"AnsweringMachines","PropertyName":"AnsweringMachinesAnsweringSystemType","IsAdvancedSearch":1,"IsGroupBy":0,"IsRequired":0},{"SubcategoryID":361,"SubcategoryName":"AnsweringMachines","PropertyName":"AnsweringMachinesRecordingTime","IsAdvancedSearch":1,"IsGroupBy":0,"IsRequired":0},{"SubcategoryID":361,"SubcategoryName":"AnsweringMachines","PropertyName":"AnsweringMachinesMailboxes","IsAdvancedSearch":0,"IsGroupBy":0,"IsRequired":0},{"SubcategoryID":361,"SubcategoryName":"AnsweringMachines","PropertyName":"AnsweringMachinesOutgoingAnnouncement","IsAdvancedSearch":0,"IsGroupBy":0,"IsRequired":0},{"SubcategoryID":361,"SubcategoryName":"AnsweringMachines","PropertyName":"AnsweringMachinesMessageIndicator","IsAdvancedSearch":0,"IsGroupBy":0,"IsRequired":0},{"SubcategoryID":361,"SubcategoryName":"AnsweringMachines","PropertyName":"AnsweringMachinesCallerID","IsAdvancedSearch":0,"IsGroupBy":0,"IsRequired":0},{"SubcategoryID":361,"SubcategoryName":"AnsweringMachines","PropertyName":"AnsweringMachinesPreprogrammedGreetingMessage","IsAdvancedSearch":0,"IsGroupBy":0,"IsRequired":0},{"SubcategoryID":361,"SubcategoryName":"AnsweringMachines","PropertyName":"AnsweringMachinesMessageTimeDateStamp","IsAdvancedSearch":0,"IsGroupBy":0,"IsRequired":0},{"SubcategoryID":361,"SubcategoryName":"AnsweringMachines","PropertyName":"AnsweringMachinesTollSaver","IsAdvancedSearch":0,"IsGroupBy":0,"IsRequired":0},{"SubcategoryID":361,"SubcategoryName":"AnsweringMachines","PropertyName":"AnsweringMachinesToneRemoteOperation","IsAdvancedSearch":0,"IsGroupBy":0,"IsRequired":0},{"SubcategoryID":361,"SubcategoryName":"AnsweringMachines","PropertyName":"AnsweringMachinesVolumeControl","IsAdvancedSearch":0,"IsGroupBy":0,"IsRequired":0},{"SubcategoryID":361,"SubcategoryName":"AnsweringMachines","PropertyName":"AnsweringMachinesVoicePrompts","IsAdvancedSearch":0,"IsGroupBy":0,"IsRequired":0},{"SubcategoryID":361,"SubcategoryName":"AnsweringMachines","PropertyName":"AnsweringMachinesPowerFailureProtection","IsAdvancedSearch":0,"IsGroupBy":0,"IsRequired":0},{"SubcategoryID":361,"SubcategoryName":"AnsweringMachines","PropertyName":"AnsweringMachinesAdditionalFeatures","IsAdvancedSearch":0,"IsGroupBy":0,"IsRequired":0},{"SubcategoryID":361,"SubcategoryName":"AnsweringMachines","PropertyName":"AnsweringMachinesDisplay","IsAdvancedSearch":0,"IsGroupBy":0,"IsRequired":0},{"SubcategoryID":361,"SubcategoryName":"AnsweringMachines","PropertyName":"AnsweringMachinesStatusIndicator","IsAdvancedSearch":0,"IsGroupBy":0,"IsRequired":0},{"SubcategoryID":361,"SubcategoryName":"AnsweringMachines","PropertyName":"AnsweringMachinesBatteryType","IsAdvancedSearch":0,"IsGroupBy":0,"IsRequired":0},{"SubcategoryID":361,"SubcategoryName":"AnsweringMachines","PropertyName":"AnsweringMachinesPlacingMounting","IsAdvancedSearch":0,"IsGroupBy":0,"IsRequired":0},{"SubcategoryID":361,"SubcategoryName":"AnsweringMachines","PropertyName":"AnsweringMachinesDimensions","IsAdvancedSearch":0,"IsGroupBy":0,"IsRequired":0},{"SubcategoryID":361,"SubcategoryName":"AnsweringMachines","PropertyName":"AnsweringMachinesWeight","IsAdvancedSearch":0,"IsGroupBy":0,"IsRequired":0},{"SubcategoryID":361,"SubcategoryName":"AnsweringMachines","PropertyName":"AnsweringMachinesDisplayFeature","IsAdvancedSearch":0,"IsGroupBy":0,"IsRequired":0},{"SubcategoryID":361,"SubcategoryName":"AnsweringMachines","PropertyName":"SportsGlobalSportsTeam","IsAdvancedSearch":0,"IsGroupBy":0,"IsRequired":0},{"SubcategoryID":361,"SubcategoryName":"AnsweringMachines","PropertyName":"SportsGlobalSportsLeague","IsAdvancedSearch":0,"IsGroupBy":0,"IsRequired":0},{"SubcategoryID":361,"SubcategoryName":"AnsweringMachines","PropertyName":"GlobalElectricalOutletPlugType","IsAdvancedSearch":0,"IsGroupBy":0,"IsRequired":0}]