{"SubcategoryID":559,"SubcategoryName":"CarAmplifiers","PropertyName":"CarSubwoofersFrequencyResponse","IsAdvancedSearch":0,"IsGroupBy":0,"IsRequired":0,"PropertyValueList":["18 Hz - 100 Hz","18 Hz - 1000 Hz","18 Hz - 2000 Hz","18 Hz - 2200 Hz","18 Hz - 2500 Hz","18 Hz - 3000 Hz","18 Hz - 500 Hz","18 Hz - 600 Hz","20 Hz - 100 Hz","20 Hz - 1000 Hz","20 Hz - 114 Hz","20 Hz - 144 Hz","20 Hz - 150 Hz","20 Hz - 1500 Hz","20 Hz - 180 Hz","20 Hz - 1800 Hz","20 Hz - 200 Hz","20 Hz - 2000 Hz","20 Hz - 220 Hz","20 Hz - 230 Hz","20 Hz - 280 Hz","20 Hz - 290 Hz","20 Hz - 300 Hz","20 Hz - 4000 Hz","20 Hz - 4500 Hz","20 Hz - 500 Hz","21 Hz - 1000 Hz","21 Hz - 150 Hz","21 Hz - 250 Hz","22 Hz - 100 Hz","22 Hz - 1000 Hz","22 Hz - 150 Hz","22 Hz - 200 Hz","22 Hz - 3000 Hz","23 Hz - 120 Hz","23 Hz - 500 Hz","24 Hz - 100 Hz","24 Hz - 1000 Hz","24 Hz - 160 Hz","24 Hz - 200 Hz","24 Hz - 250 Hz","24 Hz - 500 Hz","25 Hz - 1000 Hz","25 Hz - 1500 Hz","25 Hz - 200 Hz","25 Hz - 2000 Hz","25 Hz - 20000 Hz","25 Hz - 2200 Hz","25 Hz - 250 Hz","25 Hz - 2500 Hz","25 Hz - 3000 Hz","25 Hz - 350 Hz","25 Hz - 500 Hz","25 Hz - 600 Hz","25 Hz - 800 Hz","26 Hz - 1000 Hz","26 Hz - 200 Hz","26 Hz - 250 Hz","27 Hz - 1000 Hz","27 Hz - 150 Hz","27 Hz - 200 Hz","27 Hz - 250 Hz","27 Hz - 3000 Hz","27 Hz - 500 Hz","27 Hz - 700 Hz","28 Hz - 100 Hz","28 Hz - 1000 Hz","28 Hz - 1200 Hz","28 Hz - 125 Hz","28 Hz - 200 Hz","28 Hz - 2000 Hz","28 Hz - 2200 Hz","28 Hz - 250 Hz","28 Hz - 2500 Hz","28 Hz - 500 Hz","28 Hz - 90 Hz","29 Hz - 1000 Hz","29 Hz - 160 Hz","29 Hz - 250 Hz","29 Hz - 350 Hz","29 Hz - 450 Hz","29 Hz - 500 Hz","30 Hz - 1000 Hz","30 Hz - 120 Hz","30 Hz - 125 Hz","30 Hz - 150 Hz","30 Hz - 1500 Hz","30 Hz - 200 Hz","30 Hz - 2000 Hz","30 Hz - 2200 Hz","30 Hz - 250 Hz","30 Hz - 3000 Hz","30 Hz - 4500 Hz","30 Hz - 500 Hz","30 Hz - 700 Hz","30 Hz - 800 Hz","31 Hz - 250 Hz","31 Hz - 350 Hz","31 Hz - 450 Hz","31 Hz - 700 Hz","32 Hz - 500 Hz","33 Hz - 150 Hz","33 Hz - 400 Hz","33 Hz - 500 Hz","34 Hz - 400 Hz","35 Hz - 1000 Hz","35 Hz - 2000 Hz","35 Hz - 2200 Hz","35 Hz - 250 Hz","35 Hz - 3000 Hz","35 Hz - 3200 Hz","35 Hz - 350 Hz","35 Hz - 3500 Hz","35 Hz - 80 Hz","35 Hz - 800 Hz","35 Hz - 85 Hz","36 Hz - 250 Hz","36 Hz - 500 Hz","37 Hz - 150 Hz","38 Hz - 150 Hz","38 Hz - 280 Hz","39 Hz - 1000 Hz","39 Hz - 120 Hz","39 Hz - 150 Hz","39 Hz - 1500 Hz","39 Hz - 250 Hz","39 Hz - 85 Hz","40 Hz - 1000 Hz","40 Hz - 150 Hz","40 Hz - 3000 Hz","40 Hz - 4500 Hz","41 Hz - 150 Hz","43 Hz - 125 Hz","43 Hz - 250 Hz","45 Hz - 2000 Hz","45 Hz - 250 Hz","50 Hz - 150 Hz"]}